MANIFEST.in
README.rst
requirements.txt
setup.py
djangocms_search/__init__.py
djangocms_search/cms_plugins.py
djangocms_search/models.py
djangocms_search/paginator.py
djangocms_search/settings.py
djangocms_search/migrations/0001_initial.py
djangocms_search/migrations/__init__.py
djangocms_search/templates/djangocms_search/pagination.html
djangocms_search/templates/djangocms_search/search_items.html
djangocms_search/templates/djangocms_search/search_results_plugin.html
djangocms_search_redux.egg-info/PKG-INFO
djangocms_search_redux.egg-info/SOURCES.txt
djangocms_search_redux.egg-info/dependency_links.txt
djangocms_search_redux.egg-info/not-zip-safe
djangocms_search_redux.egg-info/requires.txt
djangocms_search_redux.egg-info/top_level.txt